[
    {
        "name": "heart",
        "data": [
            [0,0,0,0,0],
            [0,0,0,0,0],
            [0,1,0,1,0],
            [1,1,1,1,1],
            [1,1,1,1,1],
            [0,1,1,1,0],
            [0,0,1,0,0],
            [0,0,0,0,0]
        ]
    },
    {
        "name": "smile",
        "data": [
            [0,0,0,0,0],
            [0,0,0,0,0],
            [0,1,0,1,0],
            [0,0,0,0,0],
            [1,0,0,0,1],
            [0,1,1,1,0],
            [0,0,0,0,0],
            [0,0,0,0,0]
        ]
    },
    {
        "name": "smile-nose",
        "data": [
            [0,0,0,0,0],
            [0,0,0,0,0],
            [0,1,0,1,0],
            [0,0,0,0,0],
            [0,0,1,0,0],
            [1,0,0,0,1],
            [0,1,1,1,0],
            [0,0,0,0,0]
        ]
    },
    {
        "name": "alarm",
        "data": [
            [0,0,1,0,0],
            [0,1,1,1,0],
            [0,1,1,1,0],
            [0,1,1,1,0],
            [1,1,1,1,1],
            [0,0,0,0,0],
            [0,0,1,0,0],
            [0,0,0,0,0]
        ]
    },
    {
        "name": "battery-empty",
        "data": [
            [0,0,1,0,0],
            [1,1,1,1,1],
            [1,0,0,0,1],
            [1,0,0,0,1],
            [1,0,0,0,1],
            [1,0,0,0,1],
            [1,0,0,0,1],
            [1,1,1,1,1]
        ]
    },
    {
        "name": "battery-half",
        "data": [
            [0,0,1,0,0],
            [1,1,1,1,1],
            [1,0,0,0,1],
            [1,0,0,0,1],
            [1,1,1,1,1],
            [1,1,1,1,1],
            [1,1,1,1,1],
            [1,1,1,1,1]        
        ]
    },
    {
        "name": "battery-full",
        "data": [
            [0,0,1,0,0],
            [1,1,1,1,1],
            [1,1,1,1,1],
            [1,1,1,1,1],
            [1,1,1,1,1],
            [1,1,1,1,1],
            [1,1,1,1,1],
            [1,1,1,1,1]
        ]
    },
    {
        "name": "plug",
        "data": [
            [0,1,0,1,0],
            [0,1,0,1,0],
            [1,1,1,1,1],
            [1,0,0,0,1],
            [1,0,0,0,1],
            [0,1,1,1,0],
            [0,0,1,0,0],
            [0,0,1,0,0]
        ]
    },
    {
        "name": "skull",
        "data": [
            [0,0,0,0,0],
            [0,1,1,1,0],
            [1,1,1,1,1],
            [1,0,1,0,1],
            [1,1,0,1,1],
            [0,1,1,1,0],
            [0,1,1,1,0],
            [0,0,0,0,0]
        ]
    },
    {
        "name": "arrow-down",
        "data": [
            [0,0,0,0,0],
            [0,0,0,0,0],
            [0,0,1,0,0],
            [0,0,1,0,0],
            [0,0,1,0,0],
            [1,0,1,0,1],
            [0,1,1,1,0],
            [0,0,1,0,0]
        ]
    },
    {
        "name": "arrow-up",
        "data": [
            [0,0,1,0,0],
            [0,1,1,1,0],
            [1,0,1,0,1],
            [0,0,1,0,0],
            [0,0,1,0,0],
            [0,0,1,0,0],
            [0,0,0,0,0],
            [0,0,0,0,0]
        ]
    },
    {
        "name": "user",
        "data": [
            [0,0,0,0,0],
            [0,0,1,0,0],
            [0,1,1,1,0],
            [0,1,1,1,0],
            [0,0,1,0,0],
            [0,1,1,1,0],
            [1,1,1,1,1],
            [1,1,1,1,1]
        ]
    },
    {
        "name": "scroll",
        "data": [
            [0,0,1,0,0],
            [0,1,1,1,0],
            [1,0,1,0,1],
            [0,0,1,0,0],
            [0,0,1,0,0],
            [1,0,1,0,1],
            [0,1,1,1,0],
            [0,0,1,0,0]
        ]
    },
    {
        "name": "scroll-bold",
        "data": [
            [0,0,1,0,0],
            [0,1,1,1,0],
            [1,1,1,1,1],
            [0,0,1,0,0],
            [0,0,1,0,0],
            [1,1,1,1,1],
            [0,1,1,1,0],
            [0,0,1,0,0]
        ]
    }
    
]